{
    "你" : "nǐ",
    "拍" : "pāi",
    "一" : "yī",
    "我" : "wǒ",
    "了" : "le",
    "东" : "dōng",
    "西" : "xī",
    "到" : "dào",
    "呀" : "yā",
    "晓" : "xiǎo",
    "乐" : "yuè",
    "的" : "dē",
    "妈" : "mā",
    "是" : "shì",
    "中" :"Zhōng",
    "国" : "guó",
    "人" : "rén",
    "爸": "bà",
    "美": "měi",
    "那": "nà",
    "么": "me",
    "哪": "nǎ",
    "呢": "ne",
    "圆": "yuán",
    "托": "tuō",
    "尼": "ní",
    "多": "duō",
    "米": "mǐ",
    "加": "jiā",
    "汤": "tāng",
    "波": "bō",
    "兰": "lán",
    "都": "dōu",
    "还": "hái",
    "有": "yǒu",
    "在": "zài",
    "出": "chū",
    "生": "shēng",
    "他": "tā",
    "们": "mén",
    "二": "èr",
    "两": "liǎng",
    "只": "zhī",
    "小": "xiǎo",
    "鸟": "niǎo",
    "睡": "shuì",
    "觉": "jiào",
    "三": "sān",
    "画": "huà",
    "写": "xiě",
    "意": "yì",
    "四": "sì",
    "条": "tiáo",
    "腿": "tuǐ",
    "石": "shí",
    "狮": "shī",
    "子": "zǐ",
    "五": "wǔ",
    "角": "jiǎo",
    "星": "xīng",
    "亮": "liàng",
    "晶": "jīng",
    "六": "liú",
    "鸭": "yā",
    "排": "pái",
    "队": "duì",
    "走": "zǒu",
    "七": "qī",
    "色": "sè",
    "花": "huā",
    "仙": "xiān",
    "八": "bā",
    "宝": "bǎo",
    "塔": "tǎ",
    "下": "xià",
    "历": "lì",
    "史": "shǐ",
    "九": "jiǔ",
    "归": "guī",
    "重": "chóng",
    "头": "tóu",
    "来": "lái",
    "手": "shǒu",
    "欢": "huān",
    "喜": "xǐ",
    "学": "xué",
    "数": "shù",
    "姑": "gū",
    "娘": "niáng",
    "岁": "suì",
    "该": "gāi",
    "上": "shàng",
    "幼": "yòu",
    "儿": "ér",
    "园": "yuán",
    "玩": "wán",
    "具": "jù",
    "书": "shū",
    "架": "jià",
    "满": "mǎn",
    "漫": "màn",
    "哭": "kū",
    "闹": "nào",
    "故": "gù",
    "事": "shì",
    "不": "bù",
    "要": "yào",
    "个": "gè",
    "留": "liú",
    "这": "zhè",
    "里": "lǐ",
    "前": "qián",
    "后": "hòu",
    "熟": "shú",
    "悉": "xī",
    "抽": "chōu",
    "屉": "tì",
    "作": "zuò",
    "品": "pǐn",
    "集": "jí",
    "等": "děng",
    "把": "bǎ",
    "够": "gòu",
    "回": "huí",
    "家": "jiā",
    "象": "xiàng",
    "朋": "péng",
    "友": "yǒu",
    "急": "jí",
    "好": "hǎo",
    "再": "zài",
    "第": "dì",
    "天": "tiān",
    "跟": "gēn",
    "说": "shuō",
    "让": "ràng",
    "起": "qǐ",
    "分": "fēn",
    "享": "xiǎng",
    "最": "zuì",
    "近": "jìn",
    "很": "hěn",
    "胆": "dǎn",
    "陌": "mò",
    "面": "miàn",
    "她": "tā",
    "会": "huì",
    "躲": "duǒ",
    "招": "zhāo",
    "阿": "ā",
    "姨": "yí",
    "背": "bèi",
    "过": "guò",
    "脸": "liǎn",
    "抓": "zhuā",
    "着": "zhe",
    "抖": "dǒu",
    "然": "rán",
    "傻": "shǎ",
    "笑": "xiào",
    "晚": "wǎn",
    "时": "shí",
    "候": "hòu",
    "也": "yě",
    "敢": "gǎn",
    "黑": "hēi",
    "落": "luò",
    "怪": "guài",
    "物": "wù",
    "看": "kàn",
    "今": "jin",
    "从": "cóng",
    "就": "jiù",
    "开": "kāi",
    "心": "xīn",
    "问": "wèn",
    "原": "yuán",
    "圣": "shèng",
    "诞": "dàn",
    "老": "lǎo",
    "校": "xiào",
    "给": "gěi",
    "送": "sòng",
    "怕": "pà",
    "羞": "xiū",
    "所": "suǒ",
    "以": "yǐ",
    "没": "méi",
    "拿": "ná",
    "礼": "lǐ",
    "勇": "yǒng",
    "做": "zuò",
    "大": "dà",
    "女": "nǚ",
    "孩": "hái ",
    "点": "diǎn",
    "摇": "yáo",
    "体": "tǐ",
    "困": "kùn",
    "难": "nán",
    "迷": "mí",
    "藏": "cáng",
    "找": "zhǎo",
    "伴": "bàn",
    "去": "qù",
    "衣": "yī",
    "柜": "guì",
    "快": "kuài",
    "吧": "bā",
    "嘿": "hēi",
    "捉": "zhuō",
    "真": "zhēn",
    "为": "wèi",
    "什": "shí ",
    "见": "jiàn",
    "门": "mén",
    "桌": "zhuō",
    "底": "dǐ",
    "睁": "zhēng",
    "眼": "yǎn",
    "睛": "jīng",
    "床": "chuáng",
    "自": "zì",
    "己": "jǐ",
    "动": "dòng",
    "被": "bèi",
    "次": "cì",
    "早": "zǎo",
    "穿": "chuān",
    "服": "fú",
    "嘛": "ma",
    "翻": "fān",
    "身": "shēn",
    "扭": "niǔ",
    "屁": "pì",
    "股": "gǔ",
    "收": "shōu",
    "拾": "shí",
    "噘": "juē",
    "嘴": "zuǐ",
    "巴": "bā",
    "继": "jì",
    "续": "xù",
    "吃": "chī",
    "蔬": "shū",
    "菜": "cài",
    "往": "wǎng",
    "边": "biān",
    "推": "tuī",
    "先": "xiān",
    "脚": "jiǎo",
    "圈": "quān",
    "泛": "fàn",
    "泪": "lèi",
    "光": "guāng",
    "话": "huà",
    "貌": "mào",
    "暗": "àn",
    "名": "míng",
    "叫": "jiào",
    "它": "tā",
    "和": "hé",
    "坏": "huài",
    "脾": "pí",
    "气": "qì",
    "断": "duàn",
    "长": "zhǎng",
    "如": "rú",
    "果": "guǒ",
    "听": "tīng",
    "剩": "shèng",
    "孤": "gū",
    "单": "dān",
    "永": "yǒng",
    "远": "yuǎn",
    "陪": "péi",
    "跺": "duò",
    "发": "fà",
    "男": "nán",
    "裙": "qún",
    "厕": "cè",
    "摸": "mō",
    "短": "duǎn",
    "裤": "kù",
    "咬": "yǎo",
    "唇": "chún",
    "当": "dāng",
    "漂": "piào",
    "可": "kě",
    "新": "xīn",
    "道": "dào",
    "电": "diàn",
    "题": "tí",
    "胡": "hú",
    "蛋": "dàn",
    "挞": "tǎ",
    "包": "bāo",
    "外": "wài",
    "公": "gōng",
    "婆": "pó",
    "地": "dì",
    "方": "fāng",
    "坐": "zuò",
    "夜": "yè",
    "飞": "fēi",
    "机": "jī",
    "少": "shào",
    "年": "nián",
    "宫": "gōng",
    "轮": "lún",
    "翘": "qiào",
    "板": "bǎn",
    "些": "xiē",
    "叔": "shū",
    "追": "zhuī",
    "洋": "yáng",
    "娃": "wá",
    "街": "jiē",
    "特": "tè",
    "殊": "shū",
    "饼": "bǐng",
    "干": "gān",
    "能": "néng",
    "用": "yòng",
    "文": "wén",
    "处": "chǔ",
    "懂": "dǒng",
    "拉": "lā",
    "粉": "fěn",
    "红": "hóng",
    "颜": "yán",
    "爱": "ài",
    "缺": "zhèng",
    "告": "gào",
    "诉": "sù",
    "牵": "qiān",
    "商": "shāng",
    "场": "chǎng",
    "木": "mù",
    "马": "mǎ",
    "投": "tóu",
    "硬": "yìng",
    "币": "bì",
    "正": "zhèng",
    "病": "bìng",
    "鼻": "bí",
    "涕": "tì",
    "流": "liú",
    "停": "tíng",
    "咳": "ké",
    "嗽": "sou",
    "烧": "shāo",
    "全": "quán",
    "精": "jīng",
    "神": "shén",
    "医": "yī",
    "检": "jiǎn",
    "查": "chá",
    "休": "xiū",
    "息": "xī",
    "喝": "he",
    "水": "shuǐ",
    "药": "yào",
    "掉": "diào",
    "勤": "qín",
    "洗": "xǐ",
    "保": "bǎo",
    "暖": "nuǎn",
    "措": "cuò",
    "施": "shī",
    "记": "jì",
    "牢": "láo",
    "菌": "jūn",
    "划": "huà",
    "清": "qīng",
    "界": "jiè",
    "限": "xiàn",
    "健": "jiàn",
    "康": "kāng",
    "怎": "zěn",
    "办": "bàn",
    "蜜": "mì",
    "蜂": "fēng",
    "嗡": "wēng",
    "请": "qǐng",
    "传": "chuán",
    "酿": "niàng",
    "丛": "cóng",
    "忙": "máng",
    "对": "duì",
    "左": "zuǒ",
    "右": "yòu",
    "羊": "yáng",
    "桥": "qiáo",
    "央": "yāng",
    "打": "dǎ",
    "悔": "huǐ",
    "岸": "àn",
    "扑": "pū",
    "通": "tōng",
    "声": "shēng",
    "响": "xiǎng",
    "进": "jìn",
    "河": "hé",
    "雨": "yǔ",
    "蘑": "mó",
    "菇": "gu",
    "探": "tàn",
    "唱": "chàng",
    "首": "shǒu",
    "歌": "gē",
    "鹿": "lù",
    "跳": "tiào",
    "舞": "wǔ",
    "松": "sōng",
    "树": "shù",
    "爷": "yé",
    "高": "gāo",
    "兴": "xīng",
    "随": "suí",
    "风": "fēng",
    "想": "xiǎng",
    "封": "fēng",
    "信": "xìn",
    "谢": "xiè",
    "胃": "wèi",
    "口": "kǒu",
    "香": "xiāng",
    "肠": "cháng",
    "鸡": "jī",
    "报": "bào",
    "销": "xiāo",
    "忍": "rěn",
    "便": "biàn",
    "主": "zhǔ",
    "露": "lù",
    "塞": "sāi",
    "救": "jiù",
    "命": "mìng",
    "棒": "bàng",
    "疼": "téng",
    "直": "zhí",
    "山": "shān",
    "倒": "dǎo",
    "装": "zhuāng",
    "桶": "tǒng",
    "低": "dī",
    "教": "jiào",
    "训": "xùn",
    "深": "shēn",
    "刻": "kè",
    "住": "zhù",
    "肚": "dù",
    "胀": "zhàng",
    "消": "xiāo",
    "明": "míng",
    "邦": "bāng",
    "敲": "qiāo",
    "鼓": "gǔ",
    "海": "hǎi",
    "每": "měi",
    "无": "wú",
    "烦": "fán",
    "恼": "nǎo",
    "熊": "xióng",
    "买": "mǎi",
    "顶": "dǐng",
    "帽": "mào",
    "陶": "táo",
    "戴": "dài",
    "跑": "pǎo",
    "啥": "shá",
    "草": "cǎo",
    "瞧": "qiáo",
    "哈": "hā",
    "燕": "yàn",
    "粗": "cū",
    "绿": "lǜ",
    "桔": "jú",
    "黄": "huáng",
    "白": "bái"
  }